bezierv/__init__.py
bezierv/algorithms/__init__.py
bezierv/algorithms/nelder_mead.py
bezierv/algorithms/non_linear.py
bezierv/algorithms/proj_grad.py
bezierv/algorithms/proj_subgrad.py
bezierv/algorithms/utils.py
bezierv/classes/__init__.py
bezierv/classes/bezierv.py
bezierv/classes/convolver.py
bezierv/classes/distfit.py
bezierv-1.1.3.dist-info/licenses/LICENSE
bezierv-1.1.3.dist-info/METADATA
bezierv-1.1.3.dist-info/WHEEL
bezierv-1.1.3.dist-info/top_level.txt
bezierv-1.1.3.dist-info/RECORD
